{
    "production": {
        "awscloudformation": {
            "AuthRoleName": "amplify-murmur-production-74602-authRole",
            "UnauthRoleArn": "arn:aws:iam::765653276628:role/amplify-murmur-production-74602-unauthRole",
            "AuthRoleArn": "arn:aws:iam::765653276628:role/amplify-murmur-production-74602-authRole",
            "Region": "ap-northeast-1",
            "DeploymentBucketName": "amplify-murmur-production-74602-deployment",
            "UnauthRoleName": "amplify-murmur-production-74602-unauthRole",
            "StackName": "amplify-murmur-production-74602",
            "StackId": "arn:aws:cloudformation:ap-northeast-1:765653276628:stack/amplify-murmur-production-74602/9367c3b0-f937-11ea-9413-0ea105e66a72",
            "AmplifyAppId": "d1wl790wjhjciu"
        },
        "categories": {
            "auth": {
                "murmur087088ad": {}
            },
            "function": {
                "createPostAndTimeline": {}
            },
            "hosting": {
                "amplifyhosting": {
                    "appId": "d1wl790wjhjciu",
                    "type": "cicd"
                }
            }
        }
    },
    "staging": {
        "awscloudformation": {
            "AuthRoleName": "amplify-murmur-staging-125104-authRole",
            "UnauthRoleArn": "arn:aws:iam::765653276628:role/amplify-murmur-staging-125104-unauthRole",
            "AuthRoleArn": "arn:aws:iam::765653276628:role/amplify-murmur-staging-125104-authRole",
            "Region": "ap-northeast-1",
            "DeploymentBucketName": "amplify-murmur-staging-125104-deployment",
            "UnauthRoleName": "amplify-murmur-staging-125104-unauthRole",
            "StackName": "amplify-murmur-staging-125104",
            "StackId": "arn:aws:cloudformation:ap-northeast-1:765653276628:stack/amplify-murmur-staging-125104/5a1980e0-fa2b-11ea-8852-0ea0aef9ef68",
            "AmplifyAppId": "d1wl790wjhjciu"
        },
        "categories": {
            "auth": {
                "murmur087088ad": {}
            },
            "function": {
                "createPostAndTimeline": {},
                "MurmurGql": {}
            },
            "hosting": {}
        }
    },
    "design": {
        "awscloudformation": {
            "AuthRoleName": "amplify-murmur-design-60916-authRole",
            "UnauthRoleArn": "arn:aws:iam::765653276628:role/amplify-murmur-design-60916-unauthRole",
            "AuthRoleArn": "arn:aws:iam::765653276628:role/amplify-murmur-design-60916-authRole",
            "Region": "ap-northeast-1",
            "DeploymentBucketName": "amplify-murmur-design-60916-deployment",
            "UnauthRoleName": "amplify-murmur-design-60916-unauthRole",
            "StackName": "amplify-murmur-design-60916",
            "StackId": "arn:aws:cloudformation:ap-northeast-1:765653276628:stack/amplify-murmur-design-60916/624a17c0-fabc-11ea-bafa-0a648eff952a",
            "AmplifyAppId": "d1wl790wjhjciu"
        },
        "categories": {
            "auth": {
                "murmur087088ad": {}
            },
            "function": {
                "createPostAndTimeline": {},
                "MurmurGql": {}
            },
            "hosting": {
                "amplifyhosting": {
                    "appId": "d1wl790wjhjciu",
                    "type": "cicd"
                }
            }
        }
    }
}